pythia/__init__.py
pythia/basis.py
pythia/chaos.py
pythia/index.py
pythia/misc.py
pythia/parameter.py
pythia/sampler.py
pythia_uq-4.0.3.dist-info/LICENSE.Hippocratic-3.0-ECO-MEDIA-MIL.md
pythia_uq-4.0.3.dist-info/LICENSE.LGPL-3.0.md
pythia_uq-4.0.3.dist-info/LICENSE.md
pythia_uq-4.0.3.dist-info/METADATA
pythia_uq-4.0.3.dist-info/WHEEL
pythia_uq-4.0.3.dist-info/top_level.txt
pythia_uq-4.0.3.dist-info/RECORD
