Metadata-Version: 2.1
Name: pythia-uq
Version: 4.0.3
Summary: Toolbox for non-intrusive functional approximation of data via (sparse) general polynomial chaos.
Home-page: https://gitlab.com/pythia-uq/pythia
Author: Nando Hegemann
Author-email: nando.hegemann@ptb.de
Classifier: Programming Language :: Python :: 3
Classifier: Operating System :: OS Independent
License-File: LICENSE.Hippocratic-3.0-ECO-MEDIA-MIL.md
License-File: LICENSE.LGPL-3.0.md
License-File: LICENSE.md
Requires-Dist: numpy >=1.20.0
Requires-Dist: scipy >=1.5.0
Requires-Dist: psutil >=5.0
Requires-Dist: sphinx-autodoc-typehints >=1.18.1
